setup.py
dhcplib/__init__.py
dhcplib/constants.py
dhcplib/conversion.py
dhcplib/getifaddrslib.py
dhcplib/mac.py
dhcplib/net.py
dhcplib/packet.py
dhcplib/rfc.py
dhcplib/server.py
dhcplib.egg-info/PKG-INFO
dhcplib.egg-info/SOURCES.txt
dhcplib.egg-info/dependency_links.txt
dhcplib.egg-info/top_level.txt